unikud/__init__.py
unikud/framework.py
unikud-0.1.0.dist-info/METADATA
unikud-0.1.0.dist-info/WHEEL
unikud-0.1.0.dist-info/top_level.txt
unikud-0.1.0.dist-info/RECORD
